MANIFEST.in
README.rst
setup.py
docs/HISTORY.txt
docs/LICENSE.GPL
docs/LICENSE.txt
ftw/__init__.py
ftw.calendarexport.egg-info/PKG-INFO
ftw.calendarexport.egg-info/SOURCES.txt
ftw.calendarexport.egg-info/dependency_links.txt
ftw.calendarexport.egg-info/entry_points.txt
ftw.calendarexport.egg-info/namespace_packages.txt
ftw.calendarexport.egg-info/not-zip-safe
ftw.calendarexport.egg-info/requires.txt
ftw.calendarexport.egg-info/top_level.txt
ftw/calendarexport/__init__.py
ftw/calendarexport/configure.zcml
ftw/calendarexport/export.pt
ftw/calendarexport/export.py
ftw/calendarexport/results.pt
ftw/calendarexport/results.py
ftw/calendarexport/testing.py
ftw/calendarexport/locales/ftw.calendarexport.pot
ftw/calendarexport/locales/de/LC_MESSAGES/ftw.calendarexport.po
ftw/calendarexport/profiles/default/metadata.xml
ftw/calendarexport/profiles/default/propertiestool.xml
ftw/calendarexport/profiles/default/viewlets.xml
ftw/calendarexport/profiles/default/types/folder.xml
ftw/calendarexport/tests/__init__.py
ftw/calendarexport/tests/builder.py
ftw/calendarexport/tests/test_export.py
ftw/calendarexport/tests/test_export_viewlet.py