Metadata-Version: 2.1
Name: ftw.calendarexport
Version: 1.3
Summary: Export function for ftw.calendar (Maintainer: Julian Infanger)
Home-page: http://github.com/4teamwork/ftw.calendarexport
Author: 4teamwork AG
Author-email: mailto:info@4teamwork.ch
Maintainer: Julian Infanger
License: GPL2
Platform: UNKNOWN
Classifier: Framework :: Plone
Classifier: Framework :: Zope2
Classifier: Framework :: Zope3
Classifier: Programming Language :: Python
Classifier: Topic :: Software Development :: Libraries :: Python Modules
Provides-Extra: tests
